MANIFEST.in
README.rst
setup.py
ossFileField/__init__.py
ossFileField/fields.py
ossFileField/forms.py
ossFileField/utils.py
ossFileField/widgets.py
ossFileField.egg-info/PKG-INFO
ossFileField.egg-info/SOURCES.txt
ossFileField.egg-info/dependency_links.txt
ossFileField.egg-info/requires.txt
ossFileField.egg-info/top_level.txt
ossFileField/static/style.css
ossFileField/static/lib/plupload/readme.md
ossFileField/static/lib/plupload/js/Moxie.swf
ossFileField/static/lib/plupload/js/Moxie.xap
ossFileField/static/lib/plupload/js/moxie.js
ossFileField/static/lib/plupload/js/moxie.min.js
ossFileField/static/lib/plupload/js/plupload.dev.js
ossFileField/static/lib/plupload/js/plupload.full.min.js
ossFileField/static/lib/plupload/js/plupload.min.js
ossFileField/templates/ossFileField.html